tysserand/__init__.py
tysserand/tysserand.py
tysserand-0.6.0.dist-info/LICENSE
tysserand-0.6.0.dist-info/WHEEL
tysserand-0.6.0.dist-info/METADATA
tysserand-0.6.0.dist-info/RECORD
