Metadata-Version: 2.1
Name: tysserand
Version: 0.6.0
Summary: Fast and accurate spatial networks reconstruction.
License: GNU GPLv3
Author: Alexis Coullomb
Author-email: alexis.coullomb.pro@gmail.com
Requires-Python: >=3.8
Classifier: License :: Other/Proprietary License
Classifier: Programming Language :: Python :: 3
Classifier: Programming Language :: Python :: 3.10
Classifier: Programming Language :: Python :: 3.8
Classifier: Programming Language :: Python :: 3.9
Requires-Dist: dask[complete]
Requires-Dist: hdbscan
Requires-Dist: ipykernel
Requires-Dist: matplotlib
Requires-Dist: napari[all]
Requires-Dist: numpy
Requires-Dist: opencv-python-headless
Requires-Dist: pathlib
Requires-Dist: qtconsole
Requires-Dist: scikit-image
Requires-Dist: scikit-learn
Requires-Dist: scipy
Requires-Dist: seaborn
Requires-Dist: umap-learn
